<?xml version="1.0" encoding="UTF-8"  ?>
<!-- Created with iReport - A designer for JasperReports -->
<!DOCTYPE jasperReport PUBLIC "//JasperReports//DTD Report Design//EN" "http://jasperreports.sourceforge.net/dtds/jasperreport.dtd">
<jasperReport
		 name="BasicReport"
		 columnCount="1"
		 printOrder="Vertical"
		 orientation="Landscape"
		 pageWidth="842"
		 pageHeight="595"
		 columnWidth="555"
		 columnSpacing="0"
		 leftMargin="20"
		 rightMargin="20"
		 topMargin="30"
		 bottomMargin="30"
		 whenNoDataType="AllSectionsNoDetail"
		 isTitleNewPage="false"
		 isSummaryNewPage="false">
	<reportFont name="Courier_Normal" isDefault="true" fontName="Courier New" size="12" isBold="false" isItalic="false" isUnderline="false" isStrikeThrough="false" pdfFontName="Helvetica" pdfEncoding="Cp1252" isPdfEmbedded="false"/>
	<parameter name="1104" isForPrompting="true" class="java.lang.String">
		<parameterDescription><![CDATA[emptyreportVALUE]]></parameterDescription>
	</parameter>
	<parameter name="decimalseparatorVALUE" isForPrompting="true" class="java.lang.String"/>
	<parameter name="floatpatternVALUE" isForPrompting="true" class="java.lang.String">
		<parameterDescription><![CDATA[floatpatternVALUE]]></parameterDescription>
	</parameter>
	<parameter name="IsLandscape" isForPrompting="true" class="java.lang.Boolean">
		<parameterDescription><![CDATA[IsLandscape]]></parameterDescription>
	</parameter>
	<parameter name="1026" isForPrompting="true" class="java.lang.String">
		<parameterDescription><![CDATA[endofreportVALUE]]></parameterDescription>
	</parameter>
	<parameter name="moduleVALUE" isForPrompting="true" class="java.lang.String">
		<parameterDescription><![CDATA[moduleVALUE]]></parameterDescription>
	</parameter>
	<parameter name="FORMATOFECHA" isForPrompting="true" class="java.lang.String">
		<parameterDescription><![CDATA[FORMATOFECHA]]></parameterDescription>
	</parameter>
	<parameter name="titleVALUE" isForPrompting="true" class="java.lang.String">
		<parameterDescription><![CDATA[titleVALUE]]></parameterDescription>
	</parameter>
	<parameter name="DESCPAIS" isForPrompting="true" class="java.lang.String">
		<parameterDescription><![CDATA[DESCPAIS]]></parameterDescription>
	</parameter>
	<parameter name="zoneuserVALUE" isForPrompting="true" class="java.lang.String">
		<parameterDescription><![CDATA[zoneuserVALUE]]></parameterDescription>
	</parameter>
	<parameter name="countryparamVALUE" isForPrompting="true" class="java.lang.String"/>
	<parameter name="datepatternVALUE" isForPrompting="true" class="java.lang.String"/>
	<parameter name="COLUMN_1078" isForPrompting="true" class="java.lang.String"/>
	<parameter name="COLUMN_1077" isForPrompting="true" class="java.lang.String"/>
	<parameter name="COLUMN_1086" isForPrompting="true" class="java.lang.String"/>
	<parameter name="COLUMN_1087" isForPrompting="true" class="java.lang.String"/>
	<parameter name="COLUMN_1019" isForPrompting="true" class="java.lang.String"/>
	<parameter name="COLUMN_VAL_ANIO" isForPrompting="true" class="java.lang.String"/>
	<parameter name="COLUMN_1091" isForPrompting="true" class="java.lang.String"/>
	<parameter name="COLUMN_CANTIDAD" isForPrompting="true" class="java.lang.String"/>
	<parameter name="EMPTYREPORT" isForPrompting="true" class="java.lang.Boolean"/>
	<parameter name="ReportDefinitionId" isForPrompting="true" class="java.lang.String"/>
	<parameter name="1099" isForPrompting="true" class="java.lang.String"/>
	<parameter name="2541" isForPrompting="false" class="java.lang.String"/>
	<parameter name="2542" isForPrompting="false" class="java.lang.String"/>
	<parameter name="2543" isForPrompting="false" class="java.lang.String"/>
	<parameter name="2544" isForPrompting="false" class="java.lang.String"/>
	<parameter name="2545" isForPrompting="false" class="java.lang.String"/>
	<parameter name="2546" isForPrompting="false" class="java.lang.String"/>
	<parameter name="2547" isForPrompting="false" class="java.lang.String"/>
	<parameter name="2555" isForPrompting="false" class="java.lang.String"/>
	<parameter name="2556" isForPrompting="false" class="java.lang.String"/>
	<parameter name="2557" isForPrompting="false" class="java.lang.String"/>
	<parameter name="2558" isForPrompting="false" class="java.lang.String"/>
	<parameter name="2559" isForPrompting="false" class="java.lang.String"/>
	<parameter name="2560" isForPrompting="false" class="java.lang.String"/>
	<parameter name="2561" isForPrompting="false" class="java.lang.String"/>
	<parameter name="2562" isForPrompting="false" class="java.lang.String"/>
	<parameter name="2563" isForPrompting="false" class="java.lang.String"/>
	<parameter name="2564" isForPrompting="false" class="java.lang.String"/>
	<parameter name="2565" isForPrompting="false" class="java.lang.String"/>
	<parameter name="2566" isForPrompting="false" class="java.lang.String"/>
	<parameter name="IDIOMAVALUE" isForPrompting="false" class="java.lang.Long"/>
	<parameter name="1074" isForPrompting="false" class="java.lang.String"/>
	<field name="ACTIV_I18N" class="java.lang.String"/>
	<field name="1019" class="java.lang.String"/>
	<field name="1091" class="java.lang.String"/>
	<field name="1078" class="java.lang.String"/>
	<field name="VAL_ANIO" class="java.lang.String"/>
	<field name="CANTIDAD" class="java.lang.Float"/>
	<field name="DIASEM" class="java.lang.String"/>
	<field name="DIANUM" class="java.lang.String"/>
	<field name="SEMANA" class="java.lang.String"/>
	<field name="UNO" class="java.lang.String"/>
	<field name="DOS" class="java.lang.String"/>
	<field name="TRES" class="java.lang.String"/>
	<field name="CUATRO" class="java.lang.String"/>
	<field name="CINCO" class="java.lang.String"/>
	<field name="SEIS" class="java.lang.String"/>
	<field name="SIETE" class="java.lang.String"/>
	<variable name="1078CANTIDAD_SUM" class="java.lang.Float" resetType="Group" resetGroup="1078_GROUP" calculation="Sum">
		<variableExpression><![CDATA[$F{CANTIDAD}]]></variableExpression>
	</variable>
		<group  name="actividades" isStartNewColumn="false" isStartNewPage="false" isResetPageNumber="false" isReprintHeaderOnEachPage="false" minHeightToStartNewPage="0" >
			<groupExpression><![CDATA[null]]></groupExpression>
			<groupHeader>
			<band height="14"  isSplitAllowed="true" >
				<textField isStretchWithOverflow="false" pattern="" isBlankWhenNull="true" evaluationTime="Now" hyperlinkType="None" >					<reportElement
						mode="Transparent"
						x="376"
						y="0"
						width="422"
						height="14"
						forecolor="#000000"
						backcolor="#FFFFFF"
						key="textField"
						positionType="Float"
						isPrintRepeatedValues="true"
						isRemoveLineWhenBlank="false"
						isPrintInFirstWholeBand="false"
						isPrintWhenDetailOverflows="false"/>
					<textElement textAlignment="Left" verticalAlignment="Top" lineSpacing="Single">
						<font fontName="Courier_Normal" pdfFontName="Helvetica" size="10" isBold="false" isItalic="false" isUnderline="false" isPdfEmbedded ="false" pdfEncoding ="Cp1252" isStrikeThrough="false" />
					</textElement>
				<textFieldExpression   class="java.lang.String"><![CDATA[$P{COLUMN_1091}+": "+$F{1091}]]></textFieldExpression>
				</textField>
				<textField isStretchWithOverflow="false" pattern="" isBlankWhenNull="true" evaluationTime="Now" hyperlinkType="None" >					<reportElement
						mode="Transparent"
						x="2"
						y="0"
						width="178"
						height="14"
						forecolor="#000000"
						backcolor="#FFFFFF"
						key="textField"
						positionType="Float"
						isPrintRepeatedValues="true"
						isRemoveLineWhenBlank="false"
						isPrintInFirstWholeBand="false"
						isPrintWhenDetailOverflows="false"/>
					<textElement textAlignment="Left" verticalAlignment="Top" lineSpacing="Single">
						<font fontName="Courier_Normal" pdfFontName="Helvetica" size="10" isBold="false" isItalic="false" isUnderline="false" isPdfEmbedded ="false" pdfEncoding ="Cp1252" isStrikeThrough="false" />
					</textElement>
				<textFieldExpression   class="java.lang.String"><![CDATA[$P{COLUMN_1019}+": "+$F{1019}]]></textFieldExpression>
				</textField>
				<textField isStretchWithOverflow="false" pattern="" isBlankWhenNull="true" evaluationTime="Now" hyperlinkType="None" >					<reportElement
						mode="Transparent"
						x="192"
						y="0"
						width="178"
						height="14"
						forecolor="#000000"
						backcolor="#FFFFFF"
						key="textField-15"
						positionType="Float"
						isPrintRepeatedValues="true"
						isRemoveLineWhenBlank="false"
						isPrintInFirstWholeBand="false"
						isPrintWhenDetailOverflows="false"/>
					<textElement textAlignment="Left" verticalAlignment="Top" lineSpacing="Single">
						<font fontName="Courier_Normal" pdfFontName="Helvetica" size="10" isBold="false" isItalic="false" isUnderline="false" isPdfEmbedded ="false" pdfEncoding ="Cp1252" isStrikeThrough="false" />
					</textElement>
				<textFieldExpression   class="java.lang.String"><![CDATA[$P{1074}+": "+$F{VAL_ANIO}]]></textFieldExpression>
				</textField>
			</band>
			</groupHeader>
			<groupFooter>
			<band height="68"  isSplitAllowed="true" >
				<textField isStretchWithOverflow="true" pattern="" isBlankWhenNull="true" evaluationTime="Now" hyperlinkType="None" >					<reportElement
						mode="Transparent"
						x="1"
						y="8"
						width="792"
						height="60"
						forecolor="#000000"
						backcolor="#FFFFFF"
						key="textField"
						positionType="Float"
						isPrintRepeatedValues="true"
						isRemoveLineWhenBlank="false"
						isPrintInFirstWholeBand="false"
						isPrintWhenDetailOverflows="false"/>
					<textElement textAlignment="Left" verticalAlignment="Top" lineSpacing="Single">
						<font fontName="Courier New" pdfFontName="Courier" size="6" isBold="false" isItalic="false" isUnderline="false" isPdfEmbedded ="false" pdfEncoding ="Cp1252" isStrikeThrough="false" />
					</textElement>
				<textFieldExpression   class="java.lang.String"><![CDATA[$F{ACTIV_I18N}]]></textFieldExpression>
				</textField>
				<textField isStretchWithOverflow="false" pattern="" isBlankWhenNull="true" evaluationTime="Now" hyperlinkType="None" >					<reportElement
						mode="Transparent"
						x="0"
						y="0"
						width="172"
						height="8"
						forecolor="#000000"
						backcolor="#FFFFFF"
						key="textField"
						positionType="Float"
						isPrintRepeatedValues="true"
						isRemoveLineWhenBlank="false"
						isPrintInFirstWholeBand="false"
						isPrintWhenDetailOverflows="false"/>
					<textElement textAlignment="Left" verticalAlignment="Top" lineSpacing="Single">
						<font fontName="Courier_Normal" pdfFontName="Helvetica" size="6" isBold="true" isItalic="false" isUnderline="false" isPdfEmbedded ="false" pdfEncoding ="Cp1252" isStrikeThrough="false" />
					</textElement>
				<textFieldExpression   class="java.lang.String"><![CDATA[$P{1099}]]></textFieldExpression>
				</textField>
			</band>
			</groupFooter>
		</group>
		<group  name="1078_GROUP" isStartNewColumn="false" isStartNewPage="false" isResetPageNumber="false" isReprintHeaderOnEachPage="true" minHeightToStartNewPage="0" >
			<groupExpression><![CDATA[$F{1078}]]></groupExpression>
			<groupHeader>
			<band height="24"  isSplitAllowed="true" >
				<rectangle radius="0" >
					<reportElement
						mode="Transparent"
						x="630"
						y="16"
						width="80"
						height="8"
						forecolor="#000000"
						backcolor="#FFFFFF"
						key="rectangle-7"
						positionType="FixRelativeToTop"
						isPrintRepeatedValues="true"
						isRemoveLineWhenBlank="false"
						isPrintInFirstWholeBand="false"
						isPrintWhenDetailOverflows="false"/>
					<graphicElement stretchType="NoStretch" pen="Thin" fill="Solid" />
				</rectangle>
				<rectangle radius="0" >
					<reportElement
						mode="Transparent"
						x="545"
						y="16"
						width="80"
						height="8"
						forecolor="#000000"
						backcolor="#FFFFFF"
						key="rectangle-8"
						positionType="FixRelativeToTop"
						isPrintRepeatedValues="true"
						isRemoveLineWhenBlank="false"
						isPrintInFirstWholeBand="false"
						isPrintWhenDetailOverflows="false"/>
					<graphicElement stretchType="NoStretch" pen="Thin" fill="Solid" />
				</rectangle>
				<rectangle radius="0" >
					<reportElement
						mode="Transparent"
						x="460"
						y="16"
						width="80"
						height="8"
						forecolor="#000000"
						backcolor="#FFFFFF"
						key="rectangle-9"
						positionType="FixRelativeToTop"
						isPrintRepeatedValues="true"
						isRemoveLineWhenBlank="false"
						isPrintInFirstWholeBand="false"
						isPrintWhenDetailOverflows="false"/>
					<graphicElement stretchType="NoStretch" pen="Thin" fill="Solid" />
				</rectangle>
				<rectangle radius="0" >
					<reportElement
						mode="Transparent"
						x="375"
						y="16"
						width="80"
						height="8"
						forecolor="#000000"
						backcolor="#FFFFFF"
						key="rectangle-5"
						positionType="FixRelativeToTop"
						isPrintRepeatedValues="true"
						isRemoveLineWhenBlank="false"
						isPrintInFirstWholeBand="false"
						isPrintWhenDetailOverflows="false"/>
					<graphicElement stretchType="NoStretch" pen="Thin" fill="Solid" />
				</rectangle>
				<rectangle radius="0" >
					<reportElement
						mode="Transparent"
						x="290"
						y="16"
						width="80"
						height="8"
						forecolor="#000000"
						backcolor="#FFFFFF"
						key="rectangle-6"
						positionType="FixRelativeToTop"
						isPrintRepeatedValues="true"
						isRemoveLineWhenBlank="false"
						isPrintInFirstWholeBand="false"
						isPrintWhenDetailOverflows="false"/>
					<graphicElement stretchType="NoStretch" pen="Thin" fill="Solid" />
				</rectangle>
				<rectangle radius="0" >
					<reportElement
						mode="Transparent"
						x="205"
						y="16"
						width="80"
						height="8"
						forecolor="#000000"
						backcolor="#FFFFFF"
						key="rectangle-4"
						positionType="FixRelativeToTop"
						isPrintRepeatedValues="true"
						isRemoveLineWhenBlank="false"
						isPrintInFirstWholeBand="false"
						isPrintWhenDetailOverflows="false"/>
					<graphicElement stretchType="NoStretch" pen="Thin" fill="Solid" />
				</rectangle>
				<rectangle radius="0" >
					<reportElement
						mode="Transparent"
						x="120"
						y="16"
						width="80"
						height="8"
						forecolor="#000000"
						backcolor="#FFFFFF"
						key="rectangle-3"
						positionType="FixRelativeToTop"
						isPrintRepeatedValues="true"
						isRemoveLineWhenBlank="false"
						isPrintInFirstWholeBand="false"
						isPrintWhenDetailOverflows="false"/>
					<graphicElement stretchType="NoStretch" pen="Thin" fill="Solid" />
				</rectangle>
				<textField isStretchWithOverflow="true" pattern="" isBlankWhenNull="true" evaluationTime="Now" hyperlinkType="None" >					<reportElement
						mode="Transparent"
						x="82"
						y="3"
						width="696"
						height="13"
						forecolor="#000000"
						backcolor="#FFFFFF"
						key="textField"
						positionType="Float"
						isPrintRepeatedValues="true"
						isRemoveLineWhenBlank="false"
						isPrintInFirstWholeBand="false"
						isPrintWhenDetailOverflows="false"/>
					<textElement textAlignment="Left" verticalAlignment="Top" lineSpacing="Single">
						<font fontName="Courier_Normal" pdfFontName="Helvetica" size="10" isBold="false" isItalic="false" isUnderline="false" isPdfEmbedded ="false" pdfEncoding ="Cp1252" isStrikeThrough="false" />
					</textElement>
				<textFieldExpression   class="java.lang.String"><![CDATA[$F{1078}]]></textFieldExpression>
				</textField>
				<textField isStretchWithOverflow="true" pattern="" isBlankWhenNull="true" evaluationTime="Now" hyperlinkType="None" >					<reportElement
						mode="Transparent"
						x="1"
						y="3"
						width="80"
						height="13"
						forecolor="#000000"
						backcolor="#FFFFFF"
						key="textField"
						positionType="Float"
						isPrintRepeatedValues="true"
						isRemoveLineWhenBlank="false"
						isPrintInFirstWholeBand="false"
						isPrintWhenDetailOverflows="false"/>
					<textElement textAlignment="Left" verticalAlignment="Top" lineSpacing="Single">
						<font fontName="Courier_Normal" pdfFontName="Helvetica" size="10" isBold="true" isItalic="false" isUnderline="false" isPdfEmbedded ="false" pdfEncoding ="Cp1252" isStrikeThrough="false" />
					</textElement>
				<textFieldExpression   class="java.lang.String"><![CDATA[$P{COLUMN_1078}+" : "]]></textFieldExpression>
				</textField>
				<textField isStretchWithOverflow="true" pattern="" isBlankWhenNull="true" evaluationTime="Now" hyperlinkType="None" >					<reportElement
						mode="Transparent"
						x="120"
						y="16"
						width="80"
						height="8"
						forecolor="#000000"
						backcolor="#FFFFFF"
						key="textField-8"
						positionType="Float"
						isPrintRepeatedValues="true"
						isRemoveLineWhenBlank="false"
						isPrintInFirstWholeBand="false"
						isPrintWhenDetailOverflows="false"/>
					<textElement textAlignment="Center" verticalAlignment="Middle" lineSpacing="Single">
						<font fontName="Courier_Normal" pdfFontName="Helvetica" size="6" isBold="false" isItalic="false" isUnderline="false" isPdfEmbedded ="false" pdfEncoding ="Cp1252" isStrikeThrough="false" />
					</textElement>
				<textFieldExpression   class="java.lang.String"><![CDATA[$P{2541}]]></textFieldExpression>
				</textField>
				<textField isStretchWithOverflow="true" pattern="" isBlankWhenNull="true" evaluationTime="Now" hyperlinkType="None" >					<reportElement
						mode="Transparent"
						x="205"
						y="16"
						width="80"
						height="8"
						forecolor="#000000"
						backcolor="#FFFFFF"
						key="textField-9"
						positionType="Float"
						isPrintRepeatedValues="true"
						isRemoveLineWhenBlank="false"
						isPrintInFirstWholeBand="false"
						isPrintWhenDetailOverflows="false"/>
					<textElement textAlignment="Center" verticalAlignment="Middle" lineSpacing="Single">
						<font fontName="Courier_Normal" pdfFontName="Helvetica" size="6" isBold="false" isItalic="false" isUnderline="false" isPdfEmbedded ="false" pdfEncoding ="Cp1252" isStrikeThrough="false" />
					</textElement>
				<textFieldExpression   class="java.lang.String"><![CDATA[$P{2542}]]></textFieldExpression>
				</textField>
				<textField isStretchWithOverflow="true" pattern="" isBlankWhenNull="true" evaluationTime="Now" hyperlinkType="None" >					<reportElement
						mode="Transparent"
						x="375"
						y="16"
						width="80"
						height="8"
						forecolor="#000000"
						backcolor="#FFFFFF"
						key="textField-10"
						positionType="Float"
						isPrintRepeatedValues="true"
						isRemoveLineWhenBlank="false"
						isPrintInFirstWholeBand="false"
						isPrintWhenDetailOverflows="false"/>
					<textElement textAlignment="Center" verticalAlignment="Middle" lineSpacing="Single">
						<font fontName="Courier_Normal" pdfFontName="Helvetica" size="6" isBold="false" isItalic="false" isUnderline="false" isPdfEmbedded ="false" pdfEncoding ="Cp1252" isStrikeThrough="false" />
					</textElement>
				<textFieldExpression   class="java.lang.String"><![CDATA[$P{2544}]]></textFieldExpression>
				</textField>
				<textField isStretchWithOverflow="true" pattern="" isBlankWhenNull="true" evaluationTime="Now" hyperlinkType="None" >					<reportElement
						mode="Transparent"
						x="290"
						y="16"
						width="80"
						height="8"
						forecolor="#000000"
						backcolor="#FFFFFF"
						key="textField-11"
						positionType="Float"
						isPrintRepeatedValues="true"
						isRemoveLineWhenBlank="false"
						isPrintInFirstWholeBand="false"
						isPrintWhenDetailOverflows="false"/>
					<textElement textAlignment="Center" verticalAlignment="Middle" lineSpacing="Single">
						<font fontName="Courier_Normal" pdfFontName="Helvetica" size="6" isBold="false" isItalic="false" isUnderline="false" isPdfEmbedded ="false" pdfEncoding ="Cp1252" isStrikeThrough="false" />
					</textElement>
				<textFieldExpression   class="java.lang.String"><![CDATA[$P{2543}]]></textFieldExpression>
				</textField>
				<textField isStretchWithOverflow="true" pattern="" isBlankWhenNull="true" evaluationTime="Now" hyperlinkType="None" >					<reportElement
						mode="Transparent"
						x="630"
						y="16"
						width="80"
						height="8"
						forecolor="#000000"
						backcolor="#FFFFFF"
						key="textField-12"
						positionType="Float"
						isPrintRepeatedValues="true"
						isRemoveLineWhenBlank="false"
						isPrintInFirstWholeBand="false"
						isPrintWhenDetailOverflows="false"/>
					<textElement textAlignment="Center" verticalAlignment="Middle" lineSpacing="Single">
						<font fontName="Courier_Normal" pdfFontName="Helvetica" size="6" isBold="false" isItalic="false" isUnderline="false" isPdfEmbedded ="false" pdfEncoding ="Cp1252" isStrikeThrough="false" />
					</textElement>
				<textFieldExpression   class="java.lang.String"><![CDATA[$P{2547}]]></textFieldExpression>
				</textField>
				<textField isStretchWithOverflow="true" pattern="" isBlankWhenNull="true" evaluationTime="Now" hyperlinkType="None" >					<reportElement
						mode="Transparent"
						x="545"
						y="16"
						width="80"
						height="8"
						forecolor="#000000"
						backcolor="#FFFFFF"
						key="textField-13"
						positionType="Float"
						isPrintRepeatedValues="true"
						isRemoveLineWhenBlank="false"
						isPrintInFirstWholeBand="false"
						isPrintWhenDetailOverflows="false"/>
					<textElement textAlignment="Center" verticalAlignment="Middle" lineSpacing="Single">
						<font fontName="Courier_Normal" pdfFontName="Helvetica" size="6" isBold="false" isItalic="false" isUnderline="false" isPdfEmbedded ="false" pdfEncoding ="Cp1252" isStrikeThrough="false" />
					</textElement>
				<textFieldExpression   class="java.lang.String"><![CDATA[$P{2546}]]></textFieldExpression>
				</textField>
				<textField isStretchWithOverflow="true" pattern="" isBlankWhenNull="true" evaluationTime="Now" hyperlinkType="None" >					<reportElement
						mode="Transparent"
						x="460"
						y="16"
						width="80"
						height="8"
						forecolor="#000000"
						backcolor="#FFFFFF"
						key="textField-14"
						positionType="Float"
						isPrintRepeatedValues="true"
						isRemoveLineWhenBlank="false"
						isPrintInFirstWholeBand="false"
						isPrintWhenDetailOverflows="false"/>
					<textElement textAlignment="Center" verticalAlignment="Middle" lineSpacing="Single">
						<font fontName="Courier_Normal" pdfFontName="Helvetica" size="6" isBold="false" isItalic="false" isUnderline="false" isPdfEmbedded ="false" pdfEncoding ="Cp1252" isStrikeThrough="false" />
					</textElement>
				<textFieldExpression   class="java.lang.String"><![CDATA[$P{2545}]]></textFieldExpression>
				</textField>
			</band>
			</groupHeader>
			<groupFooter>
			<band height="0"  isSplitAllowed="true" >
			</band>
			</groupFooter>
		</group>
		<background>
			<band height="0"  isSplitAllowed="true" >
			</band>
		</background>
		<title>
			<band height="0"  isSplitAllowed="true" >
			</band>
		</title>
		<pageHeader>
			<band height="48"  isSplitAllowed="true" >
				<rectangle radius="0" >
					<reportElement
						mode="Transparent"
						x="0"
						y="0"
						width="800"
						height="48"
						forecolor="#000000"
						backcolor="#FFFFFF"
						key="rectangle"
						positionType="Float"
						isPrintRepeatedValues="true"
						isRemoveLineWhenBlank="false"
						isPrintInFirstWholeBand="false"
						isPrintWhenDetailOverflows="false"/>
					<graphicElement stretchType="RelativeToBandHeight" pen="2Point" fill="Solid" />
				</rectangle>
				<staticText>
					<reportElement
						mode="Transparent"
						x="1"
						y="2"
						width="100"
						height="14"
						forecolor="#000000"
						backcolor="#FFFFFF"
						key="staticText"
						positionType="Float"
						isPrintRepeatedValues="true"
						isRemoveLineWhenBlank="false"
						isPrintInFirstWholeBand="false"
						isPrintWhenDetailOverflows="false"/>
					<textElement textAlignment="Left" verticalAlignment="Top" lineSpacing="Single">
						<font fontName="Arial" pdfFontName="Helvetica" size="12" isBold="false" isItalic="false" isUnderline="false" isPdfEmbedded ="false" pdfEncoding ="Cp1252" isStrikeThrough="false" />
					</textElement>
				<text><![CDATA[BELCORP]]></text>
				</staticText>
				<textField isStretchWithOverflow="false" pattern="" isBlankWhenNull="true" evaluationTime="Now" hyperlinkType="None" >					<reportElement
						mode="Transparent"
						x="100"
						y="2"
						width="100"
						height="14"
						forecolor="#000000"
						backcolor="#FFFFFF"
						key="textField"
						positionType="Float"
						isPrintRepeatedValues="true"
						isRemoveLineWhenBlank="false"
						isPrintInFirstWholeBand="false"
						isPrintWhenDetailOverflows="false"/>
					<textElement textAlignment="Left" verticalAlignment="Top" lineSpacing="Single">
						<font fontName="Arial" pdfFontName="Helvetica" size="12" isBold="false" isItalic="false" isUnderline="false" isPdfEmbedded ="false" pdfEncoding ="Cp1252" isStrikeThrough="false" />
					</textElement>
				<textFieldExpression   class="java.lang.String"><![CDATA[$P{DESCPAIS}]]></textFieldExpression>
				</textField>
				<textField isStretchWithOverflow="false" pattern="" isBlankWhenNull="true" evaluationTime="Now" hyperlinkType="None" >					<reportElement
						mode="Transparent"
						x="1"
						y="17"
						width="100"
						height="14"
						forecolor="#000000"
						backcolor="#FFFFFF"
						key="textField"
						positionType="Float"
						isPrintRepeatedValues="true"
						isRemoveLineWhenBlank="false"
						isPrintInFirstWholeBand="false"
						isPrintWhenDetailOverflows="false"/>
					<textElement textAlignment="Left" verticalAlignment="Top" lineSpacing="Single">
						<font fontName="Arial" pdfFontName="Helvetica" size="12" isBold="false" isItalic="false" isUnderline="false" isPdfEmbedded ="false" pdfEncoding ="Cp1252" isStrikeThrough="false" />
					</textElement>
				<textFieldExpression   class="java.lang.String"><![CDATA[$P{moduleVALUE}]]></textFieldExpression>
				</textField>
				<textField isStretchWithOverflow="false" pattern="" isBlankWhenNull="true" evaluationTime="Report" hyperlinkType="None" >					<reportElement
						mode="Transparent"
						x="650"
						y="17"
						width="78"
						height="14"
						forecolor="#000000"
						backcolor="#FFFFFF"
						key="textField"
						positionType="Float"
						isPrintRepeatedValues="true"
						isRemoveLineWhenBlank="false"
						isPrintInFirstWholeBand="false"
						isPrintWhenDetailOverflows="false"/>
					<textElement textAlignment="Right" verticalAlignment="Top" lineSpacing="Single">
						<font fontName="Arial" pdfFontName="Helvetica" size="12" isBold="false" isItalic="false" isUnderline="false" isPdfEmbedded ="false" pdfEncoding ="Cp1252" isStrikeThrough="false" />
					</textElement>
				<textFieldExpression   class="java.lang.String"><![CDATA[new SimpleDateFormat($P{datepatternVALUE}).format(GregorianCalendar.getInstance().getTime())]]></textFieldExpression>
				</textField>
				<textField isStretchWithOverflow="false" pattern="" isBlankWhenNull="true" evaluationTime="Report" hyperlinkType="None" >					<reportElement
						mode="Transparent"
						x="731"
						y="17"
						width="65"
						height="14"
						forecolor="#000000"
						backcolor="#FFFFFF"
						key="textField"
						positionType="Float"
						isPrintRepeatedValues="true"
						isRemoveLineWhenBlank="false"
						isPrintInFirstWholeBand="false"
						isPrintWhenDetailOverflows="false"/>
					<textElement textAlignment="Right" verticalAlignment="Top" lineSpacing="Single">
						<font fontName="Arial" pdfFontName="Helvetica" size="12" isBold="false" isItalic="false" isUnderline="false" isPdfEmbedded ="false" pdfEncoding ="Cp1252" isStrikeThrough="false" />
					</textElement>
				<textFieldExpression   class="java.lang.String"><![CDATA[SimpleDateFormat.getTimeInstance().format(GregorianCalendar.getInstance().getTime())]]></textFieldExpression>
				</textField>
				<staticText>
					<reportElement
						mode="Transparent"
						x="679"
						y="2"
						width="30"
						height="14"
						forecolor="#000000"
						backcolor="#FFFFFF"
						key="staticText"
						positionType="Float"
						isPrintRepeatedValues="true"
						isRemoveLineWhenBlank="false"
						isPrintInFirstWholeBand="false"
						isPrintWhenDetailOverflows="false"/>
					<textElement textAlignment="Left" verticalAlignment="Top" lineSpacing="Single">
						<font fontName="Arial" pdfFontName="Helvetica" size="12" isBold="false" isItalic="false" isUnderline="false" isPdfEmbedded ="false" pdfEncoding ="Cp1252" isStrikeThrough="false" />
					</textElement>
				<text><![CDATA[Pag.]]></text>
				</staticText>
				<textField isStretchWithOverflow="false" pattern="###" isBlankWhenNull="true" evaluationTime="Now" hyperlinkType="None" >					<reportElement
						mode="Transparent"
						x="715"
						y="2"
						width="26"
						height="14"
						forecolor="#000000"
						backcolor="#FFFFFF"
						key="textField"
						positionType="Float"
						isPrintRepeatedValues="true"
						isRemoveLineWhenBlank="false"
						isPrintInFirstWholeBand="false"
						isPrintWhenDetailOverflows="false"/>
					<textElement textAlignment="Center" verticalAlignment="Top" lineSpacing="Single">
						<font fontName="Arial" pdfFontName="Helvetica" size="12" isBold="false" isItalic="false" isUnderline="false" isPdfEmbedded ="false" pdfEncoding ="Cp1252" isStrikeThrough="false" />
					</textElement>
				<textFieldExpression   class="java.lang.Integer"><![CDATA[$V{PAGE_NUMBER}]]></textFieldExpression>
				</textField>
				<staticText>
					<reportElement
						mode="Transparent"
						x="746"
						y="2"
						width="20"
						height="14"
						forecolor="#000000"
						backcolor="#FFFFFF"
						key="staticText"
						positionType="Float"
						isPrintRepeatedValues="true"
						isRemoveLineWhenBlank="false"
						isPrintInFirstWholeBand="false"
						isPrintWhenDetailOverflows="false"/>
					<textElement textAlignment="Left" verticalAlignment="Top" lineSpacing="Single">
						<font fontName="Arial" pdfFontName="Helvetica" size="12" isBold="false" isItalic="false" isUnderline="false" isPdfEmbedded ="false" pdfEncoding ="Cp1252" isStrikeThrough="false" />
					</textElement>
				<text><![CDATA[/]]></text>
				</staticText>
				<textField isStretchWithOverflow="false" pattern="###" isBlankWhenNull="true" evaluationTime="Report" hyperlinkType="None" >					<reportElement
						mode="Transparent"
						x="768"
						y="2"
						width="28"
						height="14"
						forecolor="#000000"
						backcolor="#FFFFFF"
						key="textField"
						positionType="Float"
						isPrintRepeatedValues="true"
						isRemoveLineWhenBlank="false"
						isPrintInFirstWholeBand="false"
						isPrintWhenDetailOverflows="false"/>
					<textElement textAlignment="Center" verticalAlignment="Top" lineSpacing="Single">
						<font fontName="Arial" pdfFontName="Helvetica" size="12" isBold="false" isItalic="false" isUnderline="false" isPdfEmbedded ="false" pdfEncoding ="Cp1252" isStrikeThrough="false" />
					</textElement>
				<textFieldExpression   class="java.lang.Integer"><![CDATA[$V{PAGE_NUMBER}]]></textFieldExpression>
				</textField>
				<textField isStretchWithOverflow="false" pattern="" isBlankWhenNull="true" evaluationTime="Now" hyperlinkType="None" >					<reportElement
						mode="Transparent"
						x="680"
						y="35"
						width="116"
						height="12"
						forecolor="#000000"
						backcolor="#FFFFFF"
						key="textField"
						positionType="Float"
						isPrintRepeatedValues="true"
						isRemoveLineWhenBlank="false"
						isPrintInFirstWholeBand="false"
						isPrintWhenDetailOverflows="false"/>
					<textElement textAlignment="Right" verticalAlignment="Top" lineSpacing="Single">
						<font fontName="Arial_Normal" pdfFontName="Helvetica" size="8" isBold="false" isItalic="false" isUnderline="false" isPdfEmbedded ="false" pdfEncoding ="Cp1252" isStrikeThrough="false" />
					</textElement>
				<textFieldExpression   class="java.lang.String"><![CDATA[$P{ReportDefinitionId}]]></textFieldExpression>
				</textField>
				<textField isStretchWithOverflow="false" pattern="" isBlankWhenNull="true" evaluationTime="Now" hyperlinkType="None" >					<reportElement
						mode="Transparent"
						x="1"
						y="32"
						width="100"
						height="15"
						forecolor="#000000"
						backcolor="#FFFFFF"
						key="textField"
						positionType="Float"
						isPrintRepeatedValues="true"
						isRemoveLineWhenBlank="false"
						isPrintInFirstWholeBand="false"
						isPrintWhenDetailOverflows="false"/>
					<textElement textAlignment="Left" verticalAlignment="Top" lineSpacing="Single">
						<font fontName="Arial_Normal" pdfFontName="Helvetica" size="12" isBold="false" isItalic="false" isUnderline="false" isPdfEmbedded ="false" pdfEncoding ="Cp1252" isStrikeThrough="false" />
					</textElement>
				<textFieldExpression   class="java.lang.String"><![CDATA[$P{zoneuserVALUE}]]></textFieldExpression>
				</textField>
				<textField isStretchWithOverflow="false" pattern="" isBlankWhenNull="true" evaluationTime="Now" hyperlinkType="None" >					<reportElement
						mode="Transparent"
						x="205"
						y="2"
						width="440"
						height="44"
						forecolor="#000000"
						backcolor="#FFFFFF"
						key="textField"
						positionType="Float"
						isPrintRepeatedValues="true"
						isRemoveLineWhenBlank="false"
						isPrintInFirstWholeBand="false"
						isPrintWhenDetailOverflows="false"/>
					<textElement textAlignment="Center" verticalAlignment="Top" lineSpacing="Single">
						<font fontName="Arial_Normal" pdfFontName="Helvetica" size="12" isBold="true" isItalic="false" isUnderline="false" isPdfEmbedded ="false" pdfEncoding ="Cp1252" isStrikeThrough="false" />
					</textElement>
				<textFieldExpression   class="java.lang.String"><![CDATA[$P{titleVALUE}]]></textFieldExpression>
				</textField>
				<staticText>
					<reportElement
						mode="Transparent"
						x="100"
						y="17"
						width="50"
						height="14"
						forecolor="#000000"
						backcolor="#FFFFFF"
						key="staticText"
						positionType="Float"
						isPrintRepeatedValues="true"
						isRemoveLineWhenBlank="false"
						isPrintInFirstWholeBand="false"
						isPrintWhenDetailOverflows="false"/>
					<textElement textAlignment="Left" verticalAlignment="Top" lineSpacing="Single">
						<font fontName="Arial" pdfFontName="Helvetica" size="12" isBold="false" isItalic="false" isUnderline="false" isPdfEmbedded ="false" pdfEncoding ="Cp1252" isStrikeThrough="false" />
					</textElement>
				<text><![CDATA[CRA004]]></text>
				</staticText>
			</band>
		</pageHeader>
		<columnHeader>
			<band height="1"  isSplitAllowed="true" >
			</band>
		</columnHeader>
		<detail>
			<band height="20"  isSplitAllowed="true" >
				<textField isStretchWithOverflow="true" pattern="" isBlankWhenNull="true" evaluationTime="Now" hyperlinkType="None" >					<reportElement
						mode="Transparent"
						x="120"
						y="0"
						width="80"
						height="20"
						forecolor="#000000"
						backcolor="#FFFFFF"
						key="textField"
						positionType="Float"
						isPrintRepeatedValues="true"
						isRemoveLineWhenBlank="false"
						isPrintInFirstWholeBand="false"
						isPrintWhenDetailOverflows="false"/>
					<textElement textAlignment="Center" verticalAlignment="Top" lineSpacing="Single">
						<font fontName="Courier_Normal" pdfFontName="Helvetica" size="6" isBold="false" isItalic="false" isUnderline="false" isPdfEmbedded ="false" pdfEncoding ="Cp1252" isStrikeThrough="false" />
					</textElement>
				<textFieldExpression   class="java.lang.String"><![CDATA[($F{UNO}.equalsIgnoreCase(""))?new String(""):" " + ($F{UNO}.indexOf("FESTIVO")>=0?"FESTIVO - ":"") + com.calipso.reportgenerator.reportcalculator.SharedString.newFrom($F{UNO}.substring($F{UNO}.indexOf("FESTIVO")>=0?8:0,$F{UNO}.length())).format("DD MMM","",$P{IDIOMAVALUE}) + $F{UNO}.substring($F{UNO}.indexOf("FESTIVO")>=0?18:10,$F{UNO}.length())]]></textFieldExpression>
				</textField>
				<textField isStretchWithOverflow="true" pattern="" isBlankWhenNull="true" evaluationTime="Now" hyperlinkType="None" >					<reportElement
						mode="Transparent"
						x="205"
						y="0"
						width="80"
						height="20"
						forecolor="#000000"
						backcolor="#FFFFFF"
						key="textField-1"
						positionType="Float"
						isPrintRepeatedValues="true"
						isRemoveLineWhenBlank="false"
						isPrintInFirstWholeBand="false"
						isPrintWhenDetailOverflows="false"/>
					<textElement textAlignment="Center" verticalAlignment="Top" lineSpacing="Single">
						<font fontName="Courier_Normal" pdfFontName="Helvetica" size="6" isBold="false" isItalic="false" isUnderline="false" isPdfEmbedded ="false" pdfEncoding ="Cp1252" isStrikeThrough="false" />
					</textElement>
				<textFieldExpression   class="java.lang.String"><![CDATA[($F{DOS}.equalsIgnoreCase(""))?new String(""):" " + ($F{DOS}.indexOf("FESTIVO")>=0?"FESTIVO - ":"") + com.calipso.reportgenerator.reportcalculator.SharedString.newFrom($F{DOS}.substring($F{DOS}.indexOf("FESTIVO")>=0?8:0,$F{DOS}.length())).format("DD MMM","",$P{IDIOMAVALUE}) + $F{DOS}.substring($F{DOS}.indexOf("FESTIVO")>=0?18:10,$F{DOS}.length())]]></textFieldExpression>
				</textField>
				<textField isStretchWithOverflow="true" pattern="" isBlankWhenNull="true" evaluationTime="Now" hyperlinkType="None" >					<reportElement
						mode="Transparent"
						x="290"
						y="0"
						width="80"
						height="20"
						forecolor="#000000"
						backcolor="#FFFFFF"
						key="textField-2"
						positionType="Float"
						isPrintRepeatedValues="true"
						isRemoveLineWhenBlank="false"
						isPrintInFirstWholeBand="false"
						isPrintWhenDetailOverflows="false"/>
					<textElement textAlignment="Center" verticalAlignment="Top" lineSpacing="Single">
						<font fontName="Courier_Normal" pdfFontName="Helvetica" size="6" isBold="false" isItalic="false" isUnderline="false" isPdfEmbedded ="false" pdfEncoding ="Cp1252" isStrikeThrough="false" />
					</textElement>
				<textFieldExpression   class="java.lang.String"><![CDATA[($F{TRES}.equalsIgnoreCase(""))?new String(""):" " + ($F{TRES}.indexOf("FESTIVO")>=0?"FESTIVO - ":"") + com.calipso.reportgenerator.reportcalculator.SharedString.newFrom($F{TRES}.substring($F{TRES}.indexOf("FESTIVO")>=0?8:0,$F{TRES}.length())).format("DD MMM","",$P{IDIOMAVALUE}) + $F{TRES}.substring($F{TRES}.indexOf("FESTIVO")>=0?18:10,$F{TRES}.length())]]></textFieldExpression>
				</textField>
				<textField isStretchWithOverflow="true" pattern="" isBlankWhenNull="true" evaluationTime="Now" hyperlinkType="None" >					<reportElement
						mode="Transparent"
						x="375"
						y="0"
						width="80"
						height="20"
						forecolor="#000000"
						backcolor="#FFFFFF"
						key="textField-3"
						positionType="Float"
						isPrintRepeatedValues="true"
						isRemoveLineWhenBlank="false"
						isPrintInFirstWholeBand="false"
						isPrintWhenDetailOverflows="false"/>
					<textElement textAlignment="Center" verticalAlignment="Top" lineSpacing="Single">
						<font fontName="Courier_Normal" pdfFontName="Helvetica" size="6" isBold="false" isItalic="false" isUnderline="false" isPdfEmbedded ="false" pdfEncoding ="Cp1252" isStrikeThrough="false" />
					</textElement>
				<textFieldExpression   class="java.lang.String"><![CDATA[($F{CUATRO}.equalsIgnoreCase(""))?new String(""):" " + ($F{CUATRO}.indexOf("FESTIVO")>=0?"FESTIVO - ":"") + com.calipso.reportgenerator.reportcalculator.SharedString.newFrom($F{CUATRO}.substring($F{CUATRO}.indexOf("FESTIVO")>=0?8:0,$F{CUATRO}.length())).format("DD MMM","",$P{IDIOMAVALUE}) + $F{CUATRO}.substring($F{CUATRO}.indexOf("FESTIVO")>=0?18:10,$F{CUATRO}.length())]]></textFieldExpression>
				</textField>
				<textField isStretchWithOverflow="true" pattern="" isBlankWhenNull="true" evaluationTime="Now" hyperlinkType="None" >					<reportElement
						mode="Transparent"
						x="630"
						y="0"
						width="80"
						height="20"
						forecolor="#000000"
						backcolor="#FFFFFF"
						key="textField-4"
						positionType="Float"
						isPrintRepeatedValues="true"
						isRemoveLineWhenBlank="false"
						isPrintInFirstWholeBand="false"
						isPrintWhenDetailOverflows="false"/>
					<textElement textAlignment="Center" verticalAlignment="Top" lineSpacing="Single">
						<font fontName="Courier_Normal" pdfFontName="Helvetica" size="6" isBold="false" isItalic="false" isUnderline="false" isPdfEmbedded ="false" pdfEncoding ="Cp1252" isStrikeThrough="false" />
					</textElement>
				<textFieldExpression   class="java.lang.String"><![CDATA[($F{SIETE}.equalsIgnoreCase(""))?new String(""):" " + ($F{SIETE}.indexOf("FESTIVO")>=0?"FESTIVO - ":"") + com.calipso.reportgenerator.reportcalculator.SharedString.newFrom($F{SIETE}.substring($F{SIETE}.indexOf("FESTIVO")>=0?8:0,$F{SIETE}.length())).format("DD MMM","",$P{IDIOMAVALUE}) + $F{SIETE}.substring($F{SIETE}.indexOf("FESTIVO")>=0?18:10,$F{SIETE}.length())]]></textFieldExpression>
				</textField>
				<textField isStretchWithOverflow="true" pattern="" isBlankWhenNull="true" evaluationTime="Now" hyperlinkType="None" >					<reportElement
						mode="Transparent"
						x="545"
						y="0"
						width="80"
						height="20"
						forecolor="#000000"
						backcolor="#FFFFFF"
						key="textField-6"
						positionType="Float"
						isPrintRepeatedValues="true"
						isRemoveLineWhenBlank="false"
						isPrintInFirstWholeBand="false"
						isPrintWhenDetailOverflows="false"/>
					<textElement textAlignment="Center" verticalAlignment="Top" lineSpacing="Single">
						<font fontName="Courier_Normal" pdfFontName="Helvetica" size="6" isBold="false" isItalic="false" isUnderline="false" isPdfEmbedded ="false" pdfEncoding ="Cp1252" isStrikeThrough="false" />
					</textElement>
				<textFieldExpression   class="java.lang.String"><![CDATA[($F{SEIS}.equalsIgnoreCase(""))?new String(""):" " + ($F{SEIS}.indexOf("FESTIVO")>=0?"FESTIVO - ":"") + com.calipso.reportgenerator.reportcalculator.SharedString.newFrom($F{SEIS}.substring($F{SEIS}.indexOf("FESTIVO")>=0?8:0,$F{SEIS}.length())).format("DD MMM","",$P{IDIOMAVALUE}) + $F{SEIS}.substring($F{SEIS}.indexOf("FESTIVO")>=0?18:10,$F{SEIS}.length())]]></textFieldExpression>
				</textField>
				<textField isStretchWithOverflow="true" pattern="" isBlankWhenNull="true" evaluationTime="Now" hyperlinkType="None" >					<reportElement
						mode="Transparent"
						x="460"
						y="0"
						width="80"
						height="20"
						forecolor="#000000"
						backcolor="#FFFFFF"
						key="textField-7"
						positionType="Float"
						isPrintRepeatedValues="true"
						isRemoveLineWhenBlank="false"
						isPrintInFirstWholeBand="false"
						isPrintWhenDetailOverflows="false"/>
					<textElement textAlignment="Center" verticalAlignment="Top" lineSpacing="Single">
						<font fontName="Courier_Normal" pdfFontName="Helvetica" size="6" isBold="false" isItalic="false" isUnderline="false" isPdfEmbedded ="false" pdfEncoding ="Cp1252" isStrikeThrough="false" />
					</textElement>
				<textFieldExpression   class="java.lang.String"><![CDATA[($F{CINCO}.equalsIgnoreCase(""))?new String(""):" " + ($F{CINCO}.indexOf("FESTIVO")>=0?"FESTIVO - ":"") + com.calipso.reportgenerator.reportcalculator.SharedString.newFrom($F{CINCO}.substring($F{CINCO}.indexOf("FESTIVO")>=0?8:0,$F{CINCO}.length())).format("DD MMM","",$P{IDIOMAVALUE}) + $F{CINCO}.substring($F{CINCO}.indexOf("FESTIVO")>=0?18:10,$F{CINCO}.length())]]></textFieldExpression>
				</textField>
				<rectangle radius="0" >
					<reportElement
						mode="Transparent"
						x="630"
						y="0"
						width="80"
						height="20"
						forecolor="#000000"
						backcolor="#FFFFFF"
						key="rectangle-10"
						positionType="FixRelativeToTop"
						isPrintRepeatedValues="true"
						isRemoveLineWhenBlank="false"
						isPrintInFirstWholeBand="false"
						isPrintWhenDetailOverflows="false"/>
					<graphicElement stretchType="NoStretch" pen="Thin" fill="Solid" />
				</rectangle>
				<rectangle radius="0" >
					<reportElement
						mode="Transparent"
						x="545"
						y="0"
						width="80"
						height="20"
						forecolor="#000000"
						backcolor="#FFFFFF"
						key="rectangle-11"
						positionType="FixRelativeToTop"
						isPrintRepeatedValues="true"
						isRemoveLineWhenBlank="false"
						isPrintInFirstWholeBand="false"
						isPrintWhenDetailOverflows="false"/>
					<graphicElement stretchType="NoStretch" pen="Thin" fill="Solid" />
				</rectangle>
				<rectangle radius="0" >
					<reportElement
						mode="Transparent"
						x="460"
						y="0"
						width="80"
						height="20"
						forecolor="#000000"
						backcolor="#FFFFFF"
						key="rectangle-12"
						positionType="FixRelativeToTop"
						isPrintRepeatedValues="true"
						isRemoveLineWhenBlank="false"
						isPrintInFirstWholeBand="false"
						isPrintWhenDetailOverflows="false"/>
					<graphicElement stretchType="NoStretch" pen="Thin" fill="Solid" />
				</rectangle>
				<rectangle radius="0" >
					<reportElement
						mode="Transparent"
						x="375"
						y="0"
						width="80"
						height="20"
						forecolor="#000000"
						backcolor="#FFFFFF"
						key="rectangle-13"
						positionType="FixRelativeToTop"
						isPrintRepeatedValues="true"
						isRemoveLineWhenBlank="false"
						isPrintInFirstWholeBand="false"
						isPrintWhenDetailOverflows="false"/>
					<graphicElement stretchType="NoStretch" pen="Thin" fill="Solid" />
				</rectangle>
				<rectangle radius="0" >
					<reportElement
						mode="Transparent"
						x="290"
						y="0"
						width="80"
						height="20"
						forecolor="#000000"
						backcolor="#FFFFFF"
						key="rectangle-14"
						positionType="FixRelativeToTop"
						isPrintRepeatedValues="true"
						isRemoveLineWhenBlank="false"
						isPrintInFirstWholeBand="false"
						isPrintWhenDetailOverflows="false"/>
					<graphicElement stretchType="NoStretch" pen="Thin" fill="Solid" />
				</rectangle>
				<rectangle radius="0" >
					<reportElement
						mode="Transparent"
						x="205"
						y="0"
						width="80"
						height="20"
						forecolor="#000000"
						backcolor="#FFFFFF"
						key="rectangle-15"
						positionType="FixRelativeToTop"
						isPrintRepeatedValues="true"
						isRemoveLineWhenBlank="false"
						isPrintInFirstWholeBand="false"
						isPrintWhenDetailOverflows="false"/>
					<graphicElement stretchType="NoStretch" pen="Thin" fill="Solid" />
				</rectangle>
				<rectangle radius="0" >
					<reportElement
						mode="Transparent"
						x="120"
						y="0"
						width="80"
						height="20"
						forecolor="#000000"
						backcolor="#FFFFFF"
						key="rectangle-16"
						positionType="FixRelativeToTop"
						isPrintRepeatedValues="true"
						isRemoveLineWhenBlank="false"
						isPrintInFirstWholeBand="false"
						isPrintWhenDetailOverflows="false"/>
					<graphicElement stretchType="NoStretch" pen="Thin" fill="Solid" />
				</rectangle>
			</band>
		</detail>
		<columnFooter>
			<band height="0"  isSplitAllowed="true" >
			</band>
		</columnFooter>
		<pageFooter>
			<band height="0"  isSplitAllowed="true" >
			</band>
		</pageFooter>
		<summary>
			<band height="0"  isSplitAllowed="true" >
			</band>
		</summary>
</jasperReport>
