<?xml version="1.0" encoding="UTF-8"?>
<ejb-operation>
	<pre-activation-actions>
		//System.out.println("############## Ingreso a Pre Activacion en MLNFRecibirUsuarios");
	</pre-activation-actions>
	<activator static-method="false" xsi:type="java:es.indra.mare.common.activator.EjbActivator" xmlns:xsi="http://www.w3.org/2001/XMLSchema-instance">
		<class-name>es.indra.sicc.logicanegocio.ndg.MONSincronizacionMaestro</class-name>
		<home-class>es.indra.sicc.logicanegocio.ndg.MONSincronizacionMaestroHome</home-class>
		<jndi-name>MONSincronizacionMaestro</jndi-name>
		<method-name>recibirUsuarios</method-name>
	</activator>

	<post-activation-actions>
		//System.out.println("########## Ingreso a Post Activacion en MLNFRecibirUsuarios");
	</post-activation-actions>
</ejb-operation>
